py_skyrc_charger/__init__.py
py_skyrc_charger/charger.py
py_skyrc_charger/checksum.py
py_skyrc_charger/commands.py
py_skyrc_charger-0.0.12.dist-info/METADATA
py_skyrc_charger-0.0.12.dist-info/WHEEL
py_skyrc_charger-0.0.12.dist-info/licenses/LICENSE
py_skyrc_charger-0.0.12.dist-info/RECORD
