Metadata-Version: 2.4
Name: py_skyrc_charger
Version: 0.0.12
Summary: take control of a SkyRC charger via USB
Project-URL: Homepage, https://github.com/juri117/py-skyrc-charger/
Project-URL: Issues, https://github.com/juri117/py-skyrc-charger/issues
Author-email: Juri Bieler <juri0000117@gmail.com>
License-Expression: MIT
License-File: LICENSE
Classifier: Operating System :: OS Independent
Classifier: Programming Language :: Python :: 3
Requires-Python: >=3.9
Requires-Dist: pyusb>=1.3.1
